LICENSE
MANIFEST.in
README.md
setup.cfg
setup.py
django_maploom.egg-info/PKG-INFO
django_maploom.egg-info/SOURCES.txt
django_maploom.egg-info/dependency_links.txt
django_maploom.egg-info/not-zip-safe
django_maploom.egg-info/top_level.txt
maploom/__init__.py
maploom/models.py
maploom/tests.py
maploom/geonode/__init__.py
maploom/geonode/urls.py
maploom/static/maploom/assets/MapLoom-1.7.0.css
maploom/static/maploom/assets/MapLoom-1.7.0.js
maploom/static/maploom/assets/error.png
maploom/static/maploom/assets/media-default.png
maploom/static/maploom/assets/media-error.png
maploom/static/maploom/assets/play-pause.png
maploom/static/maploom/assets/video-play.png
maploom/static/maploom/fonts/glyphicons-halflings-regular.eot
maploom/static/maploom/fonts/glyphicons-halflings-regular.svg
maploom/static/maploom/fonts/glyphicons-halflings-regular.woff
maploom/templates/maploom/_maploom_js.html
maploom/templates/maploom/_maploom_map.html
maploom/templates/maps/map_view.html
maploom/templates/maps/maploom.html
maploom/templatetags/__init__.py
maploom/templatetags/maploom_tags.py