Metadata-Version: 1.1
Name: django-maploom
Version: 1.7.0
Summary: Use MapLoom in your django projects.
Home-page: https://github.com/ROGUE-JCTD/django-maploom
Author: Prominent Edge
Author-email: geoshape.org@gmail.com
License: See LICENSE file.
Download-URL: https://github.com/ROGUE-JCTD/django-maploom
Platform: UNKNOWN
Classifier: Topic :: Utilities
Classifier: Natural Language :: English
Classifier: Operating System :: OS Independent
Classifier: Intended Audience :: Developers
Classifier: Environment :: Web Environment
Classifier: Framework :: Django
Classifier: Development Status :: 1 - Planning
Classifier: Programming Language :: Python :: 2.7
